salk_toolkit/__init__.py
salk_toolkit/_modidx.py
salk_toolkit/dashboard.py
salk_toolkit/election_models.py
salk_toolkit/io.py
salk_toolkit/plots.py
salk_toolkit/pp.py
salk_toolkit/utils.py
salk_toolkit/validation.py
salk_toolkit-0.5.4.dist-info/LICENSE
salk_toolkit-0.5.4.dist-info/METADATA
salk_toolkit-0.5.4.dist-info/WHEEL
salk_toolkit-0.5.4.dist-info/entry_points.txt
salk_toolkit-0.5.4.dist-info/top_level.txt
salk_toolkit-0.5.4.dist-info/RECORD
